polyjuice/__init__.py
polyjuice/helpers.py
polyjuice/polyjuice_wrapper.py
polyjuice/compute_perturbs/__init__.py
polyjuice/compute_perturbs/compute_ctrl_meta.py
polyjuice/compute_perturbs/compute_edit_ops.py
polyjuice/filters_and_selectors/__init__.py
polyjuice/filters_and_selectors/eval_metrics.py
polyjuice/filters_and_selectors/perplex_filter.py
polyjuice/filters_and_selectors/selections.py
polyjuice/filters_and_selectors/semantic_filter.py
polyjuice/generations/__init__.py
polyjuice/generations/create_blanks.py
polyjuice/generations/generator_helpers.py
polyjuice/generations/special_tokens.py
polyjuice_nlp-0.1.5.dist-info/LICENSE
polyjuice_nlp-0.1.5.dist-info/METADATA
polyjuice_nlp-0.1.5.dist-info/WHEEL
polyjuice_nlp-0.1.5.dist-info/top_level.txt
polyjuice_nlp-0.1.5.dist-info/RECORD
