Metadata-Version: 2.1
Name: polyjuice-nlp
Version: 0.1.5
Summary: A tool for text counterfactual generation.
Home-page: https://github.com/tongshuangwu/
Author: Tongshuang Wu
Author-email: wtshuang@cs.washington.edu
Maintainer: Tongshuang Wu
Maintainer-email: wtshuang@cs.washington.edu
License: BSD 3-Clause License
Platform: Windows
Platform: MacOS
Platform: Unix
Classifier: Development Status :: 2 - Pre-Alpha
Classifier: Intended Audience :: Science/Research
Classifier: Intended Audience :: Developers
Classifier: License :: OSI Approved :: BSD License
Classifier: Natural Language :: English
Classifier: Operating System :: Microsoft :: Windows
Classifier: Operating System :: MacOS
Classifier: Operating System :: Unix
Classifier: Programming Language :: Python
Classifier: Programming Language :: Python :: 3.6
Classifier: Programming Language :: Python :: 3.7
Classifier: Programming Language :: Python :: 3.8
Classifier: Programming Language :: Python :: 3.9
Requires-Dist: munch (>=2.5.0)
Requires-Dist: scipy
Requires-Dist: sentence-transformers (>=1.1.0)
Requires-Dist: transformers (>=4.5.1)
Requires-Dist: pattern (>=3.6.0)
Requires-Dist: nltk
Requires-Dist: zss
Requires-Dist: spacy (>=3.0.6)
